{
  "protocol_version" : "0.0.6",
  "configuration" : {
    "version" : "(6.10.0.104) (2019-12/5d03a6fe116)",
    "tlc" : "normal",
    "sigsgev" : "altstack",
    "notifications" : "kqueue",
    "architecture" : "amd64",
    "disabled_features" : "none",
    "smallconfig" : "disabled",
    "bigarrays" : "disabled",
    "softdebug" : "enabled",
    "interpreter" : "enabled",
    "llvm_support" : "0",
    "suspend" : "hybrid"
  },
  "memory" : {
    "Resident Size" : "71598080",
    "Virtual Size" : "4669366272",
    "minor_gc_time" : "0",
    "major_gc_time" : "0",
    "minor_gc_count" : "0",
    "major_gc_count" : "0",
    "major_gc_time_concurrent" : "0"
 },
  "threads" : [
 {
    "is_managed" : true,
    "offset_free_hash" : "0x17d4720dd0",
    "offset_rich_hash" : "0x17d472118a",
    "crashed" : true,
    "native_thread_id" : "0x7000050b6000",
    "thread_info_addr" : "0x7f9a58088000",
    "thread_name" : "Thread Pool Worker",
    "ctx" : {
      "IP" : "0x7fff20300462",
      "SP" : "0x7000050b4678",
      "BP" : "0x7000050b46a0"
  },
    "managed_frames" : [
  {
      "is_managed" : "false",
      "native_address" : "unregistered"
   }
,
  {
      "is_managed" : "true",
      "guid" : "55ADAE45-46CD-485B-A70E-2948332EBE8C",
      "token" : "0x00000",
      "native_offset" : "0x0",
      "filename" : "mscorlib.dll",
      "sizeofimage" : "0x474000",
      "timestamp" : "0xcdf122ed",
      "il_offset" : "0x0000c"
   }
,
  {
      "is_managed" : "true",
      "guid" : "55ADAE45-46CD-485B-A70E-2948332EBE8C",
      "token" : "0x6001f8c",
      "native_offset" : "0x0",
      "filename" : "mscorlib.dll",
      "sizeofimage" : "0x474000",
      "timestamp" : "0xcdf122ed",
      "il_offset" : "0x0001a"
   }
,
  {
      "is_managed" : "true",
      "guid" : "55ADAE45-46CD-485B-A70E-2948332EBE8C",
      "token" : "0x6001f32",
      "native_offset" : "0x0",
      "filename" : "mscorlib.dll",
      "sizeofimage" : "0x474000",
      "timestamp" : "0xcdf122ed",
      "il_offset" : "0x00028"
   }
,
  {
      "is_managed" : "true",
      "guid" : "55ADAE45-46CD-485B-A70E-2948332EBE8C",
      "token" : "0x6001f30",
      "native_offset" : "0x0",
      "filename" : "mscorlib.dll",
      "sizeofimage" : "0x474000",
      "timestamp" : "0xcdf122ed",
      "il_offset" : "0x00002"
   }
,
  {
      "is_managed" : "true",
      "guid" : "3342877D-CA78-45FD-9FAB-BE1ED45CC94F",
      "token" : "0x6000084",
      "native_offset" : "0x0",
      "filename" : "MonoDevelop.MSBuildBuilder.exe",
      "sizeofimage" : "0x14000",
      "timestamp" : "0xce43a7ab",
      "il_offset" : "0x000ae"
   }
,
  {
      "is_managed" : "true",
      "guid" : "3342877D-CA78-45FD-9FAB-BE1ED45CC94F",
      "token" : "0x6000083",
      "native_offset" : "0x0",
      "filename" : "MonoDevelop.MSBuildBuilder.exe",
      "sizeofimage" : "0x14000",
      "timestamp" : "0xce43a7ab",
      "il_offset" : "0x00001"
   }
,
  {
      "is_managed" : "true",
      "guid" : "3342877D-CA78-45FD-9FAB-BE1ED45CC94F",
      "token" : "0x600006a",
      "native_offset" : "0x0",
      "filename" : "MonoDevelop.MSBuildBuilder.exe",
      "sizeofimage" : "0x14000",
      "timestamp" : "0xce43a7ab",
      "il_offset" : "0x00048"
   }
,
  {
      "is_managed" : "true",
      "guid" : "3342877D-CA78-45FD-9FAB-BE1ED45CC94F",
      "token" : "0x60000a1",
      "native_offset" : "0x0",
      "filename" : "MonoDevelop.MSBuildBuilder.exe",
      "sizeofimage" : "0x14000",
      "timestamp" : "0xce43a7ab",
      "il_offset" : "0x00001"
   }
,
  {
      "is_managed" : "true",
      "guid" : "3342877D-CA78-45FD-9FAB-BE1ED45CC94F",
      "token" : "0x6000067",
      "native_offset" : "0x0",
      "filename" : "MonoDevelop.MSBuildBuilder.exe",
      "sizeofimage" : "0x14000",
      "timestamp" : "0xce43a7ab",
      "il_offset" : "0x00001"
   }
,
  {
      "is_managed" : "true",
      "guid" : "3342877D-CA78-45FD-9FAB-BE1ED45CC94F",
      "token" : "0x6000075",
      "native_offset" : "0x0",
      "filename" : "MonoDevelop.MSBuildBuilder.exe",
      "sizeofimage" : "0x14000",
      "timestamp" : "0xce43a7ab",
      "il_offset" : "0x00057"
   }
,
  {
      "is_managed" : "true",
      "guid" : "3342877D-CA78-45FD-9FAB-BE1ED45CC94F",
      "token" : "0x00000",
      "native_offset" : "0x0",
      "filename" : "MonoDevelop.MSBuildBuilder.exe",
      "sizeofimage" : "0x14000",
      "timestamp" : "0xce43a7ab",
      "il_offset" : "0x0002a"
   }
,
  {
      "is_managed" : "false",
      "native_address" : "unregistered"
   }
,
  {
      "is_managed" : "true",
      "guid" : "55ADAE45-46CD-485B-A70E-2948332EBE8C",
      "token" : "0x00000",
      "native_offset" : "0x0",
      "filename" : "mscorlib.dll",
      "sizeofimage" : "0x474000",
      "timestamp" : "0xcdf122ed",
      "il_offset" : "0x0000c"
   }
,
  {
      "is_managed" : "true",
      "guid" : "55ADAE45-46CD-485B-A70E-2948332EBE8C",
      "token" : "0x6004ced",
      "native_offset" : "0x0",
      "filename" : "mscorlib.dll",
      "sizeofimage" : "0x474000",
      "timestamp" : "0xcdf122ed",
      "il_offset" : "0x0006a"
   }
,
  {
      "is_managed" : "true",
      "guid" : "55ADAE45-46CD-485B-A70E-2948332EBE8C",
      "token" : "0x60048d1",
      "native_offset" : "0x0",
      "filename" : "mscorlib.dll",
      "sizeofimage" : "0x474000",
      "timestamp" : "0xcdf122ed",
      "il_offset" : "0x00000"
   }
,
  {
      "is_managed" : "true",
      "guid" : "3342877D-CA78-45FD-9FAB-BE1ED45CC94F",
      "token" : "0x6000039",
      "native_offset" : "0x0",
      "filename" : "MonoDevelop.MSBuildBuilder.exe",
      "sizeofimage" : "0x14000",
      "timestamp" : "0xce43a7ab",
      "il_offset" : "0x00019"
   }
,
  {
      "is_managed" : "true",
      "guid" : "3342877D-CA78-45FD-9FAB-BE1ED45CC94F",
      "token" : "0x6000166",
      "native_offset" : "0x0",
      "filename" : "MonoDevelop.MSBuildBuilder.exe",
      "sizeofimage" : "0x14000",
      "timestamp" : "0xce43a7ab",
      "il_offset" : "0x00029"
   }
,
  {
      "is_managed" : "true",
      "guid" : "3342877D-CA78-45FD-9FAB-BE1ED45CC94F",
      "token" : "0x6000181",
      "native_offset" : "0x0",
      "filename" : "MonoDevelop.MSBuildBuilder.exe",
      "sizeofimage" : "0x14000",
      "timestamp" : "0xce43a7ab",
      "il_offset" : "0x00001"
   }
,
  {
      "is_managed" : "true",
      "guid" : "55ADAE45-46CD-485B-A70E-2948332EBE8C",
      "token" : "0x6001ff3",
      "native_offset" : "0x0",
      "filename" : "mscorlib.dll",
      "sizeofimage" : "0x474000",
      "timestamp" : "0xcdf122ed",
      "il_offset" : "0x00007"
   }
,
  {
      "is_managed" : "true",
      "guid" : "55ADAE45-46CD-485B-A70E-2948332EBE8C",
      "token" : "0x6001ece",
      "native_offset" : "0x0",
      "filename" : "mscorlib.dll",
      "sizeofimage" : "0x474000",
      "timestamp" : "0xcdf122ed",
      "il_offset" : "0x00071"
   }
,
  {
      "is_managed" : "true",
      "guid" : "55ADAE45-46CD-485B-A70E-2948332EBE8C",
      "token" : "0x6001ecc",
      "native_offset" : "0x0",
      "filename" : "mscorlib.dll",
      "sizeofimage" : "0x474000",
      "timestamp" : "0xcdf122ed",
      "il_offset" : "0x00000"
   }
,
  {
      "is_managed" : "true",
      "guid" : "55ADAE45-46CD-485B-A70E-2948332EBE8C",
      "token" : "0x6001ff1",
      "native_offset" : "0x0",
      "filename" : "mscorlib.dll",
      "sizeofimage" : "0x474000",
      "timestamp" : "0xcdf122ed",
      "il_offset" : "0x00021"
   }
,
  {
      "is_managed" : "true",
      "guid" : "55ADAE45-46CD-485B-A70E-2948332EBE8C",
      "token" : "0x6001fd9",
      "native_offset" : "0x0",
      "filename" : "mscorlib.dll",
      "sizeofimage" : "0x474000",
      "timestamp" : "0xcdf122ed",
      "il_offset" : "0x00074"
   }
,
  {
      "is_managed" : "true",
      "guid" : "55ADAE45-46CD-485B-A70E-2948332EBE8C",
      "token" : "0x6001fee",
      "native_offset" : "0x0",
      "filename" : "mscorlib.dll",
      "sizeofimage" : "0x474000",
      "timestamp" : "0xcdf122ed",
      "il_offset" : "0x00000"
   }
,
  {
      "is_managed" : "true",
      "guid" : "55ADAE45-46CD-485B-A70E-2948332EBE8C",
      "token" : "0x00000",
      "native_offset" : "0x0",
      "filename" : "mscorlib.dll",
      "sizeofimage" : "0x474000",
      "timestamp" : "0xcdf122ed",
      "il_offset" : "0x0002a"
   }

  ],
  "unmanaged_frames" : [
 {
    "is_managed" : "false",
    "native_address" : "0x106c98346",
    "native_offset" : "0x00000"
  }
,
 {
    "is_managed" : "false",
    "native_address" : "0x106e32aa5",
    "native_offset" : "0x00000"
  }
,
 {
    "is_managed" : "false",
    "native_address" : "0x106e3311a",
    "native_offset" : "0x00000"
  }
,
 {
    "is_managed" : "false",
    "native_address" : "0x106d04da7",
    "native_offset" : "0x00000"
  }
,
 {
    "is_managed" : "false",
    "native_address" : "0x106c9cfb5",
    "native_offset" : "0x00000"
  }
,
 {
    "is_managed" : "false",
    "native_address" : "0x106d0409f",
    "native_offset" : "0x00000"
  }
,
 {
    "is_managed" : "false",
    "native_address" : "0x7fff20372d7d",
    "native_offset" : "0x00000"
  }
,
 {
    "is_managed" : "false",
    "native_address" : "unregistered"
  }
,
 {
    "is_managed" : "false",
    "native_address" : "0x7fff20281720",
    "native_offset" : "0x00000"
  }
,
 {
    "is_managed" : "false",
    "native_address" : "0x106f02397",
    "native_offset" : "0x00000"
  }
,
 {
    "is_managed" : "false",
    "native_address" : "0x106ee327f",
    "native_offset" : "0x00000"
  }
,
 {
    "is_managed" : "false",
    "native_address" : "0x106f0271e",
    "native_offset" : "0x00000"
  }
,
 {
    "is_managed" : "false",
    "native_address" : "0x106f0289f",
    "native_offset" : "0x00000"
  }
,
 {
    "is_managed" : "false",
    "native_address" : "0x106d9f059",
    "native_offset" : "0x00000"
  }
,
 {
    "is_managed" : "false",
    "native_address" : "0x106d9f5f2",
    "native_offset" : "0x00000"
  }
,
 {
    "is_managed" : "false",
    "native_address" : "0x106ef06d1",
    "native_offset" : "0x00000"
  }
,
 {
    "is_managed" : "false",
    "native_address" : "0x106ef0a70",
    "native_offset" : "0x00000"
  }
,
 {
    "is_managed" : "false",
    "native_address" : "0x106da1706",
    "native_offset" : "0x00000"
  }
,
 {
    "is_managed" : "false",
    "native_address" : "0x106dc5ab4",
    "native_offset" : "0x00000"
  }
,
 {
    "is_managed" : "true",
    "guid" : "55ADAE45-46CD-485B-A70E-2948332EBE8C",
    "token" : "0x00000",
    "native_offset" : "0x0",
    "filename" : "mscorlib.dll",
    "sizeofimage" : "0x474000",
    "timestamp" : "0xcdf122ed",
    "il_offset" : "0x00000"
  }
,
 {
    "is_managed" : "true",
    "guid" : "3342877D-CA78-45FD-9FAB-BE1ED45CC94F",
    "token" : "0x6000083",
    "native_offset" : "0x0",
    "filename" : "MonoDevelop.MSBuildBuilder.exe",
    "sizeofimage" : "0x14000",
    "timestamp" : "0xce43a7ab",
    "il_offset" : "0x00000"
  }
,
 {
    "is_managed" : "true",
    "guid" : "3342877D-CA78-45FD-9FAB-BE1ED45CC94F",
    "token" : "0x60000a1",
    "native_offset" : "0x0",
    "filename" : "MonoDevelop.MSBuildBuilder.exe",
    "sizeofimage" : "0x14000",
    "timestamp" : "0xce43a7ab",
    "il_offset" : "0x00000"
  }
,
 {
    "is_managed" : "true",
    "guid" : "3342877D-CA78-45FD-9FAB-BE1ED45CC94F",
    "token" : "0x00000",
    "native_offset" : "0x0",
    "filename" : "MonoDevelop.MSBuildBuilder.exe",
    "sizeofimage" : "0x14000",
    "timestamp" : "0xce43a7ab",
    "il_offset" : "0x00000"
  }
,
 {
    "is_managed" : "false",
    "native_address" : "0x106bfaae2",
    "native_offset" : "0x00000"
  }
,
 {
    "is_managed" : "false",
    "native_address" : "0x106e08967",
    "native_offset" : "0x00000"
  }
,
 {
    "is_managed" : "false",
    "native_address" : "0x106e11409",
    "native_offset" : "0x00000"
  }
,
 {
    "is_managed" : "false",
    "native_address" : "0x106da938d",
    "native_offset" : "0x00000"
  }
,
 {
    "is_managed" : "false",
    "native_address" : "0x106dbd027",
    "native_offset" : "0x00000"
  }
,
 {
    "is_managed" : "true",
    "guid" : "55ADAE45-46CD-485B-A70E-2948332EBE8C",
    "token" : "0x00000",
    "native_offset" : "0x0",
    "filename" : "mscorlib.dll",
    "sizeofimage" : "0x474000",
    "timestamp" : "0xcdf122ed",
    "il_offset" : "0x00000"
  }
,
 {
    "is_managed" : "true",
    "guid" : "55ADAE45-46CD-485B-A70E-2948332EBE8C",
    "token" : "0x60048d1",
    "native_offset" : "0x0",
    "filename" : "mscorlib.dll",
    "sizeofimage" : "0x474000",
    "timestamp" : "0xcdf122ed",
    "il_offset" : "0x00000"
  }
,
 {
    "is_managed" : "true",
    "guid" : "3342877D-CA78-45FD-9FAB-BE1ED45CC94F",
    "token" : "0x6000181",
    "native_offset" : "0x0",
    "filename" : "MonoDevelop.MSBuildBuilder.exe",
    "sizeofimage" : "0x14000",
    "timestamp" : "0xce43a7ab",
    "il_offset" : "0x00000"
  }
,
 {
    "is_managed" : "true",
    "guid" : "55ADAE45-46CD-485B-A70E-2948332EBE8C",
    "token" : "0x6001ecc",
    "native_offset" : "0x0",
    "filename" : "mscorlib.dll",
    "sizeofimage" : "0x474000",
    "timestamp" : "0xcdf122ed",
    "il_offset" : "0x00000"
  }
,
 {
    "is_managed" : "true",
    "guid" : "55ADAE45-46CD-485B-A70E-2948332EBE8C",
    "token" : "0x6001fee",
    "native_offset" : "0x0",
    "filename" : "mscorlib.dll",
    "sizeofimage" : "0x474000",
    "timestamp" : "0xcdf122ed",
    "il_offset" : "0x00000"
  }
,
 {
    "is_managed" : "false",
    "native_address" : "0x106bfaae2",
    "native_offset" : "0x00000"
  }
,
 {
    "is_managed" : "false",
    "native_address" : "0x106e0a342",
    "native_offset" : "0x00000"
  }
,
 {
    "is_managed" : "false",
    "native_address" : "0x106e361c7",
    "native_offset" : "0x00000"
  }
,
 {
    "is_managed" : "false",
    "native_address" : "0x106d69f88",
    "native_offset" : "0x00000"
  }
,
 {
    "is_managed" : "false",
    "native_address" : "0x106e336ed",
    "native_offset" : "0x00000"
  }
,
 {
    "is_managed" : "false",
    "native_address" : "0x7fff2032e950",
    "native_offset" : "0x00000"
  }
,
 {
    "is_managed" : "false",
    "native_address" : "0x7fff2032a47b",
    "native_offset" : "0x00000"
  }

 ]
},
{
  "is_managed" : false,
  "offset_free_hash" : "0x0",
  "offset_rich_hash" : "0x0",
  "crashed" : false,
  "native_thread_id" : "0x108ec0e00",
  "thread_info_addr" : "0x7f9a56810200",
  "thread_name" : "tid_307",
  "ctx" : {
    "IP" : "0x7fff202fc8e2",
    "SP" : "0x7ffee9017be8",
    "BP" : "0x7ffee9017c90"
 },
  "unmanaged_frames" : [
 {
    "is_managed" : "false",
    "native_address" : "0x106c98346",
    "native_offset" : "0x00000"
  }
,
 {
    "is_managed" : "false",
    "native_address" : "0x106e32aa5",
    "native_offset" : "0x00000"
  }
,
 {
    "is_managed" : "false",
    "native_address" : "0x106e327d7",
    "native_offset" : "0x00000"
  }
,
 {
    "is_managed" : "false",
    "native_address" : "0x106d03ce0",
    "native_offset" : "0x00000"
  }
,
 {
    "is_managed" : "false",
    "native_address" : "0x7fff20372d7d",
    "native_offset" : "0x00000"
  }
,
 {
    "is_managed" : "false",
    "native_address" : "0x7ffee9017a70",
    "native_offset" : "0x00000"
  }
,
 {
    "is_managed" : "false",
    "native_address" : "0x106edf430",
    "native_offset" : "0x00000"
  }
,
 {
    "is_managed" : "false",
    "native_address" : "0x106ef7401",
    "native_offset" : "0x00000"
  }
,
 {
    "is_managed" : "false",
    "native_address" : "0x106e2f9e4",
    "native_offset" : "0x00000"
  }
,
 {
    "is_managed" : "false",
    "native_address" : "0x106e2f7ea",
    "native_offset" : "0x00000"
  }
,
 {
    "is_managed" : "false",
    "native_address" : "0x106c5e30a",
    "native_offset" : "0x00000"
  }
,
 {
    "is_managed" : "false",
    "native_address" : "0x106be9e49",
    "native_offset" : "0x00000"
  }
,
 {
    "is_managed" : "false",
    "native_address" : "0x7fff20349631",
    "native_offset" : "0x00000"
  }

 ]
},
{
  "is_managed" : false,
  "offset_free_hash" : "0x0",
  "offset_rich_hash" : "0x0",
  "crashed" : false,
  "native_thread_id" : "0x7000049a7000",
  "thread_info_addr" : "0x7f9a58008200",
  "thread_name" : "Finalizer",
  "ctx" : {
    "IP" : "0x7fff202f9eba",
    "SP" : "0x7000049a6eb8",
    "BP" : "0x7000049a6f00"
 },
  "unmanaged_frames" : [
 {
    "is_managed" : "false",
    "native_address" : "0x106c98346",
    "native_offset" : "0x00000"
  }
,
 {
    "is_managed" : "false",
    "native_address" : "0x106e32aa5",
    "native_offset" : "0x00000"
  }
,
 {
    "is_managed" : "false",
    "native_address" : "0x106e327d7",
    "native_offset" : "0x00000"
  }
,
 {
    "is_managed" : "false",
    "native_address" : "0x106d03ce0",
    "native_offset" : "0x00000"
  }
,
 {
    "is_managed" : "false",
    "native_address" : "0x7fff20372d7d",
    "native_offset" : "0x00000"
  }
,
 {
    "is_managed" : "false",
    "native_address" : "unregistered"
  }
,
 {
    "is_managed" : "false",
    "native_address" : "0x106e336ed",
    "native_offset" : "0x00000"
  }
,
 {
    "is_managed" : "false",
    "native_address" : "0x7fff2032e950",
    "native_offset" : "0x00000"
  }
,
 {
    "is_managed" : "false",
    "native_address" : "0x7fff2032a47b",
    "native_offset" : "0x00000"
  }

 ]
}
]
}